src/__init__.py
src/ct.py
src/linescan.py
src/strat.py
src/xrf.py
corescan_plotting-0.9.dist-info/LICENSE
corescan_plotting-0.9.dist-info/METADATA
corescan_plotting-0.9.dist-info/WHEEL
corescan_plotting-0.9.dist-info/top_level.txt
corescan_plotting-0.9.dist-info/RECORD
