Metadata-Version: 2.1
Name: corescan-plotting
Version: 0.9
Summary: Python tools for plotting scanned core data from the USGS Pacific Coastal and Marine Science Center
Author: SeanPaul La Selle
Author-email: <slaselle@usgs.gov>
Keywords: python,geology,core,ct,xrf,linescan
Classifier: Development Status :: 1 - Planning
Classifier: Intended Audience :: Developers
Classifier: Programming Language :: Python :: 3
Classifier: Operating System :: Unix
Classifier: Operating System :: MacOS :: MacOS X
Classifier: Operating System :: Microsoft :: Windows
License-File: LICENSE
